LICENSE
README.md
setup.py
randomname/__init__.py
randomname/__main__.py
randomname/core.py
randomname/util.py
randomname.egg-info/PKG-INFO
randomname.egg-info/SOURCES.txt
randomname.egg-info/dependency_links.txt
randomname.egg-info/entry_points.txt
randomname.egg-info/requires.txt
randomname.egg-info/top_level.txt
randomname/__pyinstaller/__init__.py
randomname/__pyinstaller/hook-randomname.py
randomname/wordlists/adjectives/age.txt
randomname/wordlists/adjectives/algorithms.txt
randomname/wordlists/adjectives/appearance.txt
randomname/wordlists/adjectives/character.txt
randomname/wordlists/adjectives/colors.txt
randomname/wordlists/adjectives/complexity.txt
randomname/wordlists/adjectives/construction.txt
randomname/wordlists/adjectives/corporate_prefixes.txt
randomname/wordlists/adjectives/emotions.txt
randomname/wordlists/adjectives/food.txt
randomname/wordlists/adjectives/geometry.txt
randomname/wordlists/adjectives/linguistics.txt
randomname/wordlists/adjectives/materials.txt
randomname/wordlists/adjectives/music_theory.txt
randomname/wordlists/adjectives/physics.txt
randomname/wordlists/adjectives/quantity.txt
randomname/wordlists/adjectives/shape.txt
randomname/wordlists/adjectives/size.txt
randomname/wordlists/adjectives/sound.txt
randomname/wordlists/adjectives/speed.txt
randomname/wordlists/adjectives/taste.txt
randomname/wordlists/adjectives/temperature.txt
randomname/wordlists/adjectives/weather.txt
randomname/wordlists/ipsum/corporate.txt
randomname/wordlists/ipsum/crypto.txt
randomname/wordlists/ipsum/hipster.txt
randomname/wordlists/ipsum/lorem.txt
randomname/wordlists/ipsum/reddit.txt
randomname/wordlists/names/cities/alpha.txt
randomname/wordlists/names/cities/canada.txt
randomname/wordlists/names/cities/city_states.txt
randomname/wordlists/names/cities/france.txt
randomname/wordlists/names/cities/ireland.txt
randomname/wordlists/names/cities/netherlands.txt
randomname/wordlists/names/cities/spain.txt
randomname/wordlists/names/cities/switzerland.txt
randomname/wordlists/names/cities/united_states.txt
randomname/wordlists/names/codenames/apple.txt
randomname/wordlists/names/codenames/intel.txt
randomname/wordlists/names/codenames/microsoft.txt
