Metadata-Version: 2.1
Name: randomname
Version: 0.2.1
Summary: Generate random adj-noun names like docker and github.
Home-page: https://github.com/beasteers/randomname
Author: Bea Steers
Author-email: bea.steers@gmail.com
License: MIT License
Keywords: random name generator docker container github repo word list noun adjective verb
Platform: UNKNOWN
Classifier: License :: OSI Approved :: MIT License
Classifier: Programming Language :: Python :: 3.7
Classifier: Programming Language :: Python :: 3.8
Classifier: Programming Language :: Python :: 3.9
